CLA.md
CODE_OF_CONDUCT.md
CONTRIBUTING.md
MANIFEST.in
README.md
RELEASE_NOTES.md
requirements-test.txt
requirements.txt
setup.cfg
setup.py
bitshares/__init__.py
bitshares/account.py
bitshares/aes.py
bitshares/amount.py
bitshares/asset.py
bitshares/bitshares.py
bitshares/block.py
bitshares/blockchain.py
bitshares/blockchainobject.py
bitshares/committee.py
bitshares/dex.py
bitshares/exceptions.py
bitshares/fee.py
bitshares/instance.py
bitshares/market.py
bitshares/memo.py
bitshares/message.py
bitshares/notify.py
bitshares/price.py
bitshares/proposal.py
bitshares/storage.py
bitshares/transactionbuilder.py
bitshares/utils.py
bitshares/vesting.py
bitshares/wallet.py
bitshares/witness.py
bitshares/worker.py
bitsharesapi/__init__.py
bitsharesapi/bitsharesnoderpc.py
bitsharesapi/exceptions.py
bitsharesapi/websocket.py
bitsharesbase/__init__.py
bitsharesbase/account.py
bitsharesbase/asset_permissions.py
bitsharesbase/bip38.py
bitsharesbase/chains.py
bitsharesbase/memo.py
bitsharesbase/objects.py
bitsharesbase/objecttypes.py
bitsharesbase/operationids.py
bitsharesbase/operations.py
bitsharesbase/signedtransactions.py
bitsharesbase/transactions.py
quantadex.egg-info/PKG-INFO
quantadex.egg-info/SOURCES.txt
quantadex.egg-info/dependency_links.txt
quantadex.egg-info/requires.txt
quantadex.egg-info/top_level.txt