Metadata-Version: 1.2
Name: quantadex
Version: 1.2.1
Summary: Python library for quantadex
Home-page: https://github.com/quantadex/python-bitshares
Author: cryptoQuoc
Author-email: quoc@quantadex.com
Maintainer: cryptoQuoc
Maintainer-email: quocble@gmail.com
License: UNKNOWN
Download-URL: https://github.com/quantadex/python-bitshares/tarball/1.2.1
Keywords: bitshares,library,api,rpc
Platform: UNKNOWN
Classifier: License :: OSI Approved :: MIT License
Classifier: Operating System :: OS Independent
Classifier: Programming Language :: Python :: 3
Classifier: Development Status :: 3 - Alpha
Classifier: Intended Audience :: Developers
Classifier: Intended Audience :: Financial and Insurance Industry
Classifier: Topic :: Office/Business :: Financial
